uhull/__init__.py
uhull/alpha_shape.py
uhull/geometry.py
uhull/graph.py
uhull-0.1.2.dist-info/METADATA
uhull-0.1.2.dist-info/WHEEL
uhull-0.1.2.dist-info/RECORD
