Metadata-Version: 2.1
Name: uhull
Version: 0.1.2
Summary: A simple (but not simpler) algorithm for concave hull of 2D point sets using an alpha shape algorithm.
Home-page: https://luanleonardo.github.io/uhull/
Author: Luan Leonardo
Author-email: llvdmoraes@gmail.com
Requires-Python: >=3.9,<3.13
Classifier: Programming Language :: Python :: 3
Classifier: Programming Language :: Python :: 3.9
Classifier: Programming Language :: Python :: 3.10
Classifier: Programming Language :: Python :: 3.11
Requires-Dist: numpy (>=1.22)
Requires-Dist: scipy (>=1.10.0,<2.0.0)
Project-URL: Repository, https://github.com/luanleonardo/uhull
